bash2gitlab/__about__.py
bash2gitlab/__init__.py
bash2gitlab/__main__.py
bash2gitlab/builtin_plugins.py
bash2gitlab/config.py
bash2gitlab/gui.py
bash2gitlab/hookspecs.py
bash2gitlab/install_help.py
bash2gitlab/interactive.py
bash2gitlab/plugins.py
bash2gitlab/py.typed
bash2gitlab/tui.py
bash2gitlab/watch_files.py
bash2gitlab/commands/__init__.py
bash2gitlab/commands/autogit.py
bash2gitlab/commands/best_effort_runner.py
bash2gitlab/commands/clean_all.py
bash2gitlab/commands/compile_all.py
bash2gitlab/commands/compile_bash_reader.py
bash2gitlab/commands/compile_not_bash.py
bash2gitlab/commands/copy2local.py
bash2gitlab/commands/decompile_all.py
bash2gitlab/commands/detect_drift.py
bash2gitlab/commands/doctor.py
bash2gitlab/commands/doctor_checks.py
bash2gitlab/commands/graph_all.py
bash2gitlab/commands/init_project.py
bash2gitlab/commands/inline_clone_and_run.py
bash2gitlab/commands/input_change_detector.py
bash2gitlab/commands/lint_all.py
bash2gitlab/commands/map_commit.py
bash2gitlab/commands/map_deploy.py
bash2gitlab/commands/pipeline_docs.py
bash2gitlab/commands/pipeline_trigger.py
bash2gitlab/commands/precommit.py
bash2gitlab/commands/show_config.py
bash2gitlab/commands/upgrade_pinned_templates.py
bash2gitlab/commands/validate_all.py
bash2gitlab/errors/__init__.py
bash2gitlab/errors/exceptions.py
bash2gitlab/errors/exit_codes.py
bash2gitlab/schemas/NOTICE.txt
bash2gitlab/schemas/gitlab_ci_schema.json
bash2gitlab/utils/__init__.py
bash2gitlab/utils/check_interactive.py
bash2gitlab/utils/cli_suggestions.py
bash2gitlab/utils/diff_helpers.py
bash2gitlab/utils/dotenv.py
bash2gitlab/utils/logging_config.py
bash2gitlab/utils/missing_tkinter.py
bash2gitlab/utils/mock_ci_vars.py
bash2gitlab/utils/parse_bash.py
bash2gitlab/utils/pathlib_polyfills.py
bash2gitlab/utils/temp_env.py
bash2gitlab/utils/terminal_colors.py
bash2gitlab/utils/toml_reader.py
bash2gitlab/utils/update_checker.py
bash2gitlab/utils/urllib3_helper.py
bash2gitlab/utils/utils.py
bash2gitlab-0.9.9.dist-info/METADATA
bash2gitlab-0.9.9.dist-info/WHEEL
bash2gitlab-0.9.9.dist-info/entry_points.txt
bash2gitlab-0.9.9.dist-info/licenses/AUTHORS.md
bash2gitlab-0.9.9.dist-info/licenses/LICENSE
bash2gitlab-0.9.9.dist-info/RECORD
