Metadata-Version: 2.4
Name: bash2gitlab
Version: 0.9.9
Summary: Compile bash to gitlab pipeline yaml
Project-URL: Repository, https://github.com/matthewdeanmartin/bash2gitlab
Project-URL: Documentation, https://bash2gitlab.readthedocs.io/en/latest/
Project-URL: Changelog, https://github.com/matthewdeanmartin/bash2gitlab/blob/main/CHANGELOG.md
Project-URL: homepage, https://github.com/matthewdeanmartin/bash2gitlab
Project-URL: issues, https://github.com/matthewdeanmartin/bash2gitlab/issues/
Author-email: Matthew Martin <matthewdeanmartin@gmail.com>
License-Expression: MIT
License-File: AUTHORS.md
License-File: LICENSE
Keywords: bash,gitlab
Classifier: Development Status :: 4 - Beta
Classifier: Intended Audience :: Developers
Classifier: License :: OSI Approved :: MIT License
Classifier: Operating System :: OS Independent
Classifier: Programming Language :: Python
Classifier: Programming Language :: Python :: 3.8
Classifier: Programming Language :: Python :: 3.9
Classifier: Programming Language :: Python :: 3.10
Classifier: Programming Language :: Python :: 3.11
Classifier: Programming Language :: Python :: 3.12
Classifier: Programming Language :: Python :: 3.13
Classifier: Programming Language :: Python :: 3.14
Requires-Python: >=3.8
Requires-Dist: certifi
Requires-Dist: importlib-resources
Requires-Dist: jsonschema
Requires-Dist: orjson
Requires-Dist: pluggy
Requires-Dist: python-gitlab
Requires-Dist: rtoml
Requires-Dist: ruamel-yaml
Requires-Dist: toml
Requires-Dist: urllib3
Provides-Extra: all
Requires-Dist: argcomplete; extra == 'all'
Requires-Dist: colorlog; extra == 'all'
Requires-Dist: graphviz; extra == 'all'
Requires-Dist: matplotlib; extra == 'all'
Requires-Dist: packaging; extra == 'all'
Requires-Dist: pyvis; extra == 'all'
Requires-Dist: rich; extra == 'all'
Requires-Dist: rich-argparse; extra == 'all'
Requires-Dist: textual; extra == 'all'
Requires-Dist: tomli; (python_version < '3.11') and extra == 'all'
Requires-Dist: tomlkit; extra == 'all'
Requires-Dist: watchdog>=3.0.0; extra == 'all'
